aws_nsm_interface_verifiably/__init__.py
aws_nsm_interface_verifiably/exceptions.py
aws_nsm_interface_verifiably/structs.py
aws_nsm_interface_verifiably-1.0.1.dist-info/LICENSE
aws_nsm_interface_verifiably-1.0.1.dist-info/METADATA
aws_nsm_interface_verifiably-1.0.1.dist-info/WHEEL
aws_nsm_interface_verifiably-1.0.1.dist-info/top_level.txt
aws_nsm_interface_verifiably-1.0.1.dist-info/RECORD
