Metadata-Version: 2.1
Name: aws-nsm-interface-verifiably
Version: 1.0.1
Summary: Native Python interface for the AWS Nitro Secure Module (NSM)
Home-page: https://github.com/verifiably/aws-nsm-interface-verifiably
Author: Verifiably
Author-email: contact@verifiably.com
License: UNKNOWN
Platform: UNKNOWN
Classifier: Programming Language :: Python :: 3
Classifier: License :: OSI Approved :: MIT License
Classifier: Operating System :: OS Independent
Requires-Python: >=3.6
Requires-Dist: cbor2 (>=5.2.0)
Requires-Dist: ioctl-opt (>=1.2.2)
